Metadata-Version: 2.1
Name: testPACKesthon
Version: 0.0.1
Summary: A very application
Home-page: UNKNOWN
Author: Matt
Author-email: nullie@g.m
License: MIT
Keywords: test
Platform: UNKNOWN
Classifier: Development Status :: 5 - Production/Stable
Classifier: Intended Audience :: Education
Classifier: Operating System :: Microsoft :: Windows :: Windows 10
Classifier: License :: OSI Approved :: MIT License
Classifier: Programming Language :: Python :: 3
License-File: LICENSE.txt
